CHANGES.txt
MANIFEST.in
README.md
README.rst
requirements.txt
setup.py
src/udemy-dl
src/udemy_dl/__init__.py
src/udemy_dl/__main__.py
src/udemy_dl/_version.py
src/udemy_dl/download.py
src/udemy_dl/udemy_dl.py
udemy_dl.egg-info/PKG-INFO
udemy_dl.egg-info/SOURCES.txt
udemy_dl.egg-info/dependency_links.txt
udemy_dl.egg-info/requires.txt
udemy_dl.egg-info/top_level.txt