Metadata-Version: 1.1
Name: udemy-dl
Version: 0.2.0
Summary: Download videos from Udemy for personal offline use
Home-page: https://github.com/nishad/udemy-dl
Author: Gaganpreet Singh Arora
Author-email: gaganpreet.arora@gmail.com
License: UNKNOWN
Platform: UNKNOWN
Classifier: Environment :: Console
Classifier: Programming Language :: Python :: 2
Classifier: Programming Language :: Python :: 3
Classifier: Topic :: Multimedia :: Video
